resvg_wasi/__init__.py
resvg_wasi/resvg.wasm
resvg_wasi/usvg.wasm
resvg_wasi-0.31.0.dist-info/METADATA
resvg_wasi-0.31.0.dist-info/WHEEL
resvg_wasi-0.31.0.dist-info/entry_points.txt
resvg_wasi-0.31.0.dist-info/top_level.txt
resvg_wasi-0.31.0.dist-info/RECORD
